{
    "DARKVISION": {
        "title": "Darkvision",
        "description": "You can see in dim light within 60 feet of you as if it were bright light, and within darkness as if it was dim light."
    },
    "MENACING": {
        "title": "Menacing",
        "description": "You gain proficiency in the Intimidation skill."
    },
    "RELENTLESS ENDURANCE": {
        "title": "Relentless Endurance",
        "description": "When you are reduced to 0 hit points but not killed outright, you can drop to 1 hit point instead. You can't use this feature again until you finish a long rest."
    },
    "SAVAGE ATTACKS": {
        "title": "Savage Attacks",
        "description": "When you score a critical hit with a melee weapon attack, you can roll one of the weapon's damage dice one additional time and add it to the extra damage of the critical hit."
    }
}